setup.py
shinkenplugins/__init__.py
shinkenplugins.plugins.drupal_codebase.egg-info/PKG-INFO
shinkenplugins.plugins.drupal_codebase.egg-info/SOURCES.txt
shinkenplugins.plugins.drupal_codebase.egg-info/dependency_links.txt
shinkenplugins.plugins.drupal_codebase.egg-info/entry_points.txt
shinkenplugins.plugins.drupal_codebase.egg-info/namespace_packages.txt
shinkenplugins.plugins.drupal_codebase.egg-info/requires.txt
shinkenplugins.plugins.drupal_codebase.egg-info/top_level.txt
shinkenplugins/plugins/__init__.py
shinkenplugins/plugins/drupal_codebase/__init__.py
shinkenplugins/plugins/drupal_codebase/drupal_codebase.py